emoticon/emoticon.py
emoticon-1.0.5.dist-info/LICENSE.txt
emoticon-1.0.5.dist-info/METADATA
emoticon-1.0.5.dist-info/WHEEL
emoticon-1.0.5.dist-info/top_level.txt
emoticon-1.0.5.dist-info/RECORD
