Metadata-Version: 2.1
Name: emoticon
Version: 1.0.5
Summary: python package to transform any emoticon to text or its meaning
Home-page: UNKNOWN
Author: Ega Febri Dharmawan
Author-email: egafebridh@gmail.com
License: MIT
Platform: UNKNOWN
Classifier: Programming Language :: Python :: 3.8
Classifier: Programming Language :: Python :: 3
Classifier: Programming Language :: Python :: 3.7
Classifier: License :: OSI Approved :: MIT License
Requires-Dist: NLTK
Requires-Dist: mtranslate
Requires-Dist: csv
